text_file/manifest.toml
text_file/text_file.py
opsbox_text_file_output-0.1.3.dist-info/LICENCE.txt
opsbox_text_file_output-0.1.3.dist-info/METADATA
opsbox_text_file_output-0.1.3.dist-info/WHEEL
opsbox_text_file_output-0.1.3.dist-info/entry_points.txt
opsbox_text_file_output-0.1.3.dist-info/top_level.txt
opsbox_text_file_output-0.1.3.dist-info/RECORD
